geotech_pandas/__init__.py
geotech_pandas/accessor.py
geotech_pandas/base.py
geotech_pandas/helpers.py
geotech_pandas/layer.py
geotech_pandas/point.py
geotech_pandas/py.typed
geotech_pandas/utils.py
geotech_pandas/in_situ/__init__.py
geotech_pandas/in_situ/in_situ.py
geotech_pandas/in_situ/spt.py
geotech_pandas/lab/__init__.py
geotech_pandas/lab/index.py
geotech_pandas/lab/lab.py
geotech_pandas-0.3.0.dist-info/METADATA
geotech_pandas-0.3.0.dist-info/WHEEL
geotech_pandas-0.3.0.dist-info/licenses/LICENSE.md
geotech_pandas-0.3.0.dist-info/RECORD
