Metadata-Version: 2.4
Name: geotech-pandas
Version: 0.3.0
Summary: A Pandas extension for geotechnical calculations.
Project-URL: homepage, https://github.com/fraserdominicdavid/geotech-pandas
Project-URL: source, https://github.com/fraserdominicdavid/geotech-pandas
Project-URL: changelog, https://github.com/fraserdominicdavid/geotech-pandas/blob/main/CHANGELOG.md
Project-URL: releasenotes, https://github.com/fraserdominicdavid/geotech-pandas/releases
Project-URL: documentation, https://github.com/fraserdominicdavid/geotech-pandas
Project-URL: issues, https://github.com/fraserdominicdavid/geotech-pandas/issues
Author-email: Fraser Dominic David <77269589+fraserdominicdavid@users.noreply.github.com>
License-File: LICENSE.md
Requires-Python: <4.0,>=3.10
Requires-Dist: numpy>=2.2.4
Requires-Dist: pandas>=2.1.2
Requires-Dist: statsmodels>=0.14.4
